crash2json/__init__.py
crash2json/__main__.py
crash2json/_binary_image.py
crash2json/_crash2json.py
crash2json/_crashed_thread_state.py
crash2json/_diagnostic_message.py
crash2json/_exception_backtrace.py
crash2json/_exception_information.py
crash2json/_header.py
crash2json/_other_threads_backtrace.py
crash2json/_trigger_thread_backtrace.py
crash2json-3.0.dist-info/METADATA
crash2json-3.0.dist-info/WHEEL
crash2json-3.0.dist-info/entry_points.txt
crash2json-3.0.dist-info/top_level.txt
crash2json-3.0.dist-info/RECORD
