Metadata-Version: 2.1
Name: crash2json
Version: 3.0
Summary: Parse appple crash report to json file
Home-page: https://github.com/yanbo92/crash2json
Author: yanbo92
Author-email: yanbo92@139.com
License: UNKNOWN
Platform: UNKNOWN
